setup.py
tinyec/__init__.py
tinyec/ec.py
tinyec/registry.py
tinyec.egg-info/PKG-INFO
tinyec.egg-info/SOURCES.txt
tinyec.egg-info/dependency_links.txt
tinyec.egg-info/top_level.txt