Metadata-Version: 1.1
Name: tinyec
Version: 0.3
Summary: A tiny library to perform arithmetic operations on elliptic curves in pure python
Home-page: https://github.com/alexmgr/tinyec
Author: Alex Moneger
Author-email: alexmgr+github@gmail.com
License: GPLv3
Download-URL: https://github.com/alexmgr/tinyec/archive/v0.3.tar.gz
Keywords: elliptic,curves,crypto,tls,ssl,ecdhe,diffie-hellman
Platform: UNKNOWN
